Metadata-Version: 2.1
Name: linkedin-job-profile-scraper-with-python
Version: 1.0.1
Summary: A python library to scrape job profile data from linkedin automatically.
Home-page: https://linkedin-api.datakund.com/en/latest/
Author: DataKund
Author-email: datakund@gmail.com
License: Apache License 2.0
Keywords: linkedin python bot_studio scraper job profile data web-scraping
Platform: UNKNOWN
